{
    "doc_id": 94,
    "city": "London",
    "region_code": "ENG",
    "os": null,
    "tags": [],
    "ip": 1347912168,
    "isp": "The Positive Internet Company Ltd",
    "area_code": null,
    "longitude": -0.12574,
    "last_update": "2022-03-25T00:50:26.977910",
    "ports": [
      80,
      443
    ],
    "latitude": 51.50853,
    "hostnames": [
      "fry-vip-01.positive-dedicated.net",
      "staging.stephenfry.com"
    ],
    "country_code": "GB",
    "country_name": "United Kingdom",
    "domains": [
      "positive-dedicated.net",
      "stephenfry.com"
    ],
    "org": "Positive Infrastructure",
    "data": [
      {
        "hash": 1914632335,
        "product": "nginx",
        "hostnames": [
          "fry-vip-01.positive-dedicated.net"
        ],
        "http": {
          "status": 302,
          "robots_hash": null,
          "redirects": [],
          "securitytxt": null,
          "title": "302 Found",
          "sitemap_hash": null,
          "robots": null,
          "server": "nginx/1.18.0",
          "host": "80.87.129.232",
          "html": "<html>\r\n<head><title>302 Found</title></head>\r\n<body>\r\n<center><h1>302 Found</h1></center>\r\n<hr><center>nginx/1.18.0</center>\r\n</body>\r\n</html>\r\n",
          "location": "/",
          "components": {},
          "html_hash": -1671440734,
          "sitemap": null,
          "securitytxt_hash": null
        },
        "ip": 1347912168,
        "org": "Positive Infrastructure",
        "isp": "The Positive Internet Company Ltd",
        "transport": "tcp",
        "cpe": [
          "cpe:/a:igor_sysoev:nginx:1.18.0"
        ],
        "data": "HTTP/1.1 302 Moved Temporarily\r\nServer: nginx/1.18.0\r\nDate: Fri, 25 Mar 2022 00:46:41 GMT\r\nContent-Type: text/html\r\nContent-Length: 145\r\nConnection: keep-alive\r\nLocation: https://80.87.129.232/\r\n\r\n",
        "asn": "AS21260",
        "port": 80,
        "version": "1.18.0",
        "cpe23": [
          "cpe:2.3:a:igor_sysoev:nginx:1.18.0"
        ],
        "timestamp": "2022-03-25T00:46:41.343856",
        "domains": [
          "positive-dedicated.net"
        ],
        "ip_str": "80.87.129.232",
        "os": null,
        "_shodan": {
          "crawler": "3f1279c6853212fb475ce5da28a7fdac617a5bd4",
          "options": {},
          "id": "9fe4098c-1a4c-434d-9e80-41a86edd0ae1",
          "module": "http",
          "ptr": true
        },
        "opts": {},
        "location": {
          "city": "London",
          "region_code": "ENG",
          "area_code": null,
          "longitude": -0.12574,
          "latitude": 51.50853,
          "country_code": "GB",
          "country_name": "United Kingdom"
        }
      },
      {
        "ip": 1347912168,
        "http": {
          "status": 200,
          "robots_hash": null,
          "redirects": [],
          "securitytxt": null,
          "title": "Apache2 Debian Default Page: It works",
          "sitemap_hash": null,
          "waf": "CacheWall (Varnish)",
          "robots": null,
          "server": "nginx/1.18.0",
          "host": "80.87.129.232",
          "html": "\n<!DOCTYPE html PUBLIC \"-//W3C//DTD XHTML 1.0 Transitional//EN\" \"http://www.w3.org/TR/xhtml1/DTD/xhtml1-transitional.dtd\">\n<html xmlns=\"http://www.w3.org/1999/xhtml\">\n  <head>\n    <meta http-equiv=\"Content-Type\" content=\"text/html; charset=UTF-8\" />\n    <title>Apache2 Debian Default Page: It works</title>\n    <style type=\"text/css\" media=\"screen\">\n  * {\n    margin: 0px 0px 0px 0px;\n    padding: 0px 0px 0px 0px;\n  }\n\n  body, html {\n    padding: 3px 3px 3px 3px;\n\n    background-color: #D8DBE2;\n\n    font-family: Verdana, sans-serif;\n    font-size: 11pt;\n    text-align: center;\n  }\n\n  div.main_page {\n    position: relative;\n    display: table;\n\n    width: 800px;\n\n    margin-bottom: 3px;\n    margin-left: auto;\n    margin-right: auto;\n    padding: 0px 0px 0px 0px;\n\n    border-width: 2px;\n    border-color: #212738;\n    border-style: solid;\n\n    background-color: #FFFFFF;\n\n    text-align: center;\n  }\n\n  div.page_header {\n    height: 99px;\n    width: 100%;\n\n    background-color: #F5F6F7;\n  }\n\n  div.page_header span {\n    margin: 15px 0px 0px 50px;\n\n    font-size: 180%;\n    font-weight: bold;\n  }\n\n  div.page_header img {\n    margin: 3px 0px 0px 40px;\n\n    border: 0px 0px 0px;\n  }\n\n  div.table_of_contents {\n    clear: left;\n\n    min-width: 200px;\n\n    margin: 3px 3px 3px 3px;\n\n    background-color: #FFFFFF;\n\n    text-align: left;\n  }\n\n  div.table_of_contents_item {\n    clear: left;\n\n    width: 100%;\n\n    margin: 4px 0px 0px 0px;\n\n    background-color: #FFFFFF;\n\n    color: #000000;\n    text-align: left;\n  }\n\n  div.table_of_contents_item a {\n    margin: 6px 0px 0px 6px;\n  }\n\n  div.content_section {\n    margin: 3px 3px 3px 3px;\n\n    background-color: #FFFFFF;\n\n    text-align: left;\n  }\n\n  div.content_section_text {\n    padding: 4px 8px 4px 8px;\n\n    color: #000000;\n    font-size: 100%;\n  }\n\n  div.content_section_text pre {\n    margin: 8px 0px 8px 0px;\n    padding: 8px 8px 8px 8px;\n\n    border-width: 1px;\n    border-style: dotted;\n    border-color: #000000;\n\n    background-color: #F5F6F7;\n\n    font-style: italic;\n  }\n\n  div.content_section_text p {\n    margin-bottom: 6px;\n  }\n\n  div.content_section_text ul, div.content_section_text li {\n    padding: 4px 8px 4px 16px;\n  }\n\n  div.section_header {\n    padding: 3px 6px 3px 6px;\n\n    background-color: #8E9CB2;\n\n    color: #FFFFFF;\n    font-weight: bold;\n    font-size: 112%;\n    text-align: center;\n  }\n\n  div.section_header_red {\n    background-color: #CD214F;\n  }\n\n  div.section_header_grey {\n    background-color: #9F9386;\n  }\n\n  .floating_element {\n    position: relative;\n    float: left;\n  }\n\n  div.table_of_contents_item a,\n  div.content_section_text a {\n    text-decoration: none;\n    font-weight: bold;\n  }\n\n  div.table_of_contents_item a:link,\n  div.table_of_contents_item a:visited,\n  div.table_of_contents_item a:active {\n    color: #000000;\n  }\n\n  div.table_of_contents_item a:hover {\n    background-color: #000000;\n\n    color: #FFFFFF;\n  }\n\n  div.content_section_text a:link,\n  div.content_section_text a:visited,\n   div.content_section_text a:active {\n    background-color: #DCDFE6;\n\n    color: #000000;\n  }\n\n  div.content_section_text a:hover {\n    background-color: #000000;\n\n    color: #DCDFE6;\n  }\n\n  div.validator {\n  }\n    </style>\n  </head>\n  <body>\n    <div class=\"main_page\">\n      <div class=\"page_header floating_element\">\n        <img src=\"/icons/openlogo-75.png\" alt=\"Debian Logo\" class=\"floating_element\"/>\n        <span class=\"floating_element\">\n          Apache2 Debian Default Page\n        </span>\n      </div>\n<!--      <div class=\"table_of_contents floating_element\">\n        <div class=\"section_header section_header_grey\">\n          TABLE OF CONTENTS\n        </div>\n        <div class=\"table_of_contents_item floating_element\">\n          <a href=\"#about\">About</a>\n        </div>\n        <div class=\"table_of_contents_item floating_element\">\n          <a href=\"#changes\">Changes</a>\n        </div>\n        <div class=\"table_of_contents_item floating_element\">\n          <a href=\"#scope\">Scope</a>\n        </div>\n        <div class=\"table_of_contents_item floating_element\">\n          <a href=\"#files\">Config files</a>\n        </div>\n      </div>\n-->\n      <div class=\"content_section floating_element\">\n\n\n        <div class=\"section_header section_header_red\">\n          <div id=\"about\"></div>\n          It works!\n        </div>\n        <div class=\"content_section_text\">\n          <p>\n                This is the default welcome page used to test the correct \n                operation of the Apache2 server after installation on Debian systems.\n                If you can read this page, it means that the Apache HTTP server installed at\n                this site is working properly. You should <b>replace this file</b> (located at\n                <tt>/var/www/html/index.html</tt>) before continuing to operate your HTTP server.\n          </p>\n\n\n          <p>\n                If you are a normal user of this web site and don't know what this page is\n                about, this probably means that the site is currently unavailable due to\n                maintenance.\n                If the problem persists, please contact the site's administrator.\n          </p>\n\n        </div>\n        <div class=\"section_header\">\n          <div id=\"changes\"></div>\n                Configuration Overview\n        </div>\n        <div class=\"content_section_text\">\n          <p>\n                Debian's Apache2 default configuration is different from the\n                upstream default configuration, and split into several files optimized for\n                interaction with Debian tools. The configuration system is\n                <b>fully documented in\n                /usr/share/doc/apache2/README.Debian.gz</b>. Refer to this for the full\n                documentation. Documentation for the web server itself can be\n                found by accessing the <a href=\"/manual\">manual</a> if the <tt>apache2-doc</tt>\n                package was installed on this server.\n\n          </p>\n          <p>\n                The configuration layout for an Apache2 web server installation on Debian systems is as follows:\n          </p>\n          <pre>\n/etc/apache2/\n|-- apache2.conf\n|       `--  ports.conf\n|-- mods-enabled\n|       |-- *.load\n|       `-- *.conf\n|-- conf-enabled\n|       `-- *.conf\n|-- sites-enabled\n|       `-- *.conf\n          </pre>\n          <ul>\n                        <li>\n                           <tt>apache2.conf</tt> is the main configuration\n                           file. It puts the pieces together by including all remaining configuration\n                           files when starting up the web server.\n                        </li>\n\n                        <li>\n                           <tt>ports.conf</tt> is always included from the\n                           main configuration file. It is used to determine the listening ports for\n                           incoming connections, and this file can be customized anytime.\n                        </li>\n\n                        <li>\n                           Configuration files in the <tt>mods-enabled/</tt>,\n                           <tt>conf-enabled/</tt> and <tt>sites-enabled/</tt> directories contain\n                           particular configuration snippets which manage modules, global configuration\n                           fragments, or virtual host configurations, respectively.\n                        </li>\n\n                        <li>\n                           They are activated by symlinking available\n                           configuration files from their respective\n                           *-available/ counterparts. These should be managed\n                           by using our helpers\n                           <tt>\n                                a2enmod,\n                                a2dismod,\n                           </tt>\n                           <tt>\n                                a2ensite,\n                                a2dissite,\n                            </tt>\n                                and\n                           <tt>\n                                a2enconf,\n                                a2disconf\n                           </tt>. See their respective man pages for detailed information.\n                        </li>\n\n                        <li>\n                           The binary is called apache2. Due to the use of\n                           environment variables, in the default configuration, apache2 needs to be\n                           started/stopped with <tt>/etc/init.d/apache2</tt> or <tt>apache2ctl</tt>.\n                           <b>Calling <tt>/usr/bin/apache2</tt> directly will not work</b> with the\n                           default configuration.\n                        </li>\n          </ul>\n        </div>\n\n        <div class=\"section_header\">\n            <div id=\"docroot\"></div>\n                Document Roots\n        </div>\n\n        <div class=\"content_section_text\">\n            <p>\n                By default, Debian does not allow access through the web browser to\n                <em>any</em> file apart of those located in <tt>/var/www</tt>,\n                <a href=\"http://httpd.apache.org/docs/2.4/mod/mod_userdir.html\" rel=\"nofollow\">public_html</a>\n                directories (when enabled) and <tt>/usr/share</tt> (for web\n                applications). If your site is using a web document root\n                located elsewhere (such as in <tt>/srv</tt>) you may need to whitelist your\n                document root directory in <tt>/etc/apache2/apache2.conf</tt>.\n            </p>\n            <p>\n                The default Debian document root is <tt>/var/www/html</tt>. You\n                can make your own virtual hosts under /var/www. This is different\n                to previous releases which provides better security out of the box.\n            </p>\n        </div>\n\n        <div class=\"section_header\">\n          <div id=\"bugs\"></div>\n                Reporting Problems\n        </div>\n        <div class=\"content_section_text\">\n          <p>\n                Please use the <tt>reportbug</tt> tool to report bugs in the\n                Apache2 package with Debian. However, check <a\n                href=\"http://bugs.debian.org/cgi-bin/pkgreport.cgi?ordering=normal;archive=0;src=apache2;repeatmerged=0\"\n                rel=\"nofollow\">existing bug reports</a> before reporting a new bug.\n          </p>\n          <p>\n                Please report bugs specific to modules (such as PHP and others)\n                to respective packages, not to the web server itself.\n          </p>\n        </div>\n\n\n\n\n      </div>\n    </div>\n    <div class=\"validator\">\n    </div>\n  </body>\n</html>\n\n",
          "location": "/",
          "components": {},
          "html_hash": -567627901,
          "sitemap": null,
          "securitytxt_hash": null
        },
        "port": 443,
        "transport": "tcp",
        "version": "1.18.0",
        "location": {
          "city": "London",
          "region_code": "ENG",
          "area_code": null,
          "longitude": -0.12574,
          "latitude": 51.50853,
          "country_code": "GB",
          "country_name": "United Kingdom"
        },
        "product": "nginx",
        "hash": 773068352,
        "timestamp": "2022-03-25T00:50:26.977910",
        "ssl": {
          "chain_sha256": [
            "f81b66fb065678bc87afcaf078749654ce9272fa7bc8641db180e535e3c7e0c6",
            "67add1166b020ae61b8f5fc96813c04c2aa589960796865572a3c7e737613dfd",
            "96bcec06264976f37460779acf28c5a7cfe8a3c0aae11a8ffcee05c0bddf08c6"
          ],
          "jarm": "2ad2ad0002ad2ad00042d42d0000005d86ccb1a0567e012264097a0315d7a7",
          "chain": [
            "-----BEGIN CERTIFICATE-----\nMIIFMzCCBBugAwIBAgISA5wDDd1UsmK1AInXYEi4mYBoMA0GCSqGSIb3DQEBCwUA\nMDIxCzAJBgNVBAYTAlVTMRYwFAYDVQQKEw1MZXQncyBFbmNyeXB0MQswCQYDVQQD\nEwJSMzAeFw0yMjAzMDYyMDEwNTJaFw0yMjA2MDQyMDEwNTFaMCExHzAdBgNVBAMT\nFnN0YWdpbmcuc3RlcGhlbmZyeS5jb20wggEiMA0GCSqGSIb3DQEBAQUAA4IBDwAw\nggEKAoIBAQDSuEui6syMrbSe4WEnxfhQyIXBvoueuXgiZIBX905iHj59xpJIg+BM\nS/s8VaZGMS7y9QvXbct0CCs0mrnhvS1sgaV2IXHGLYZRzQ6bLmKmAT9Zy5OsH9qL\n8nq9Xlzxlq0BBg1mVAnW5Jdpfmzha1giQl7t4SHqk89kEVBuNImyHhKepbpz8/b4\n9R4zcyANV4m2SUZDzDurVz2tirubmp/oeSKLre3zM/7ULEz8U29oXO53raP6ZNXG\nOtixwa3hXUuwR6lssx0kv6OwF1VOuZwBWf9Yif33urPne3Rzl58hGir0RoF/ywdB\nsBdMnnawDeTyCve994DiLIwtOyt3A8Y1AgMBAAGjggJSMIICTjAOBgNVHQ8BAf8E\nBAMCBaAwHQYDVR0lBBYwFAYIKwYBBQUHAwEGCCsGAQUFBwMCMAwGA1UdEwEB/wQC\nMAAwHQYDVR0OBBYEFEF1Ss6U8qXUiOpG3gpUIrd7Dt0IMB8GA1UdIwQYMBaAFBQu\nsxe3WFbLrlAJQOYfr52LFMLGMFUGCCsGAQUFBwEBBEkwRzAhBggrBgEFBQcwAYYV\naHR0cDovL3IzLm8ubGVuY3Iub3JnMCIGCCsGAQUFBzAChhZodHRwOi8vcjMuaS5s\nZW5jci5vcmcvMCEGA1UdEQQaMBiCFnN0YWdpbmcuc3RlcGhlbmZyeS5jb20wTAYD\nVR0gBEUwQzAIBgZngQwBAgEwNwYLKwYBBAGC3xMBAQEwKDAmBggrBgEFBQcCARYa\naHR0cDovL2Nwcy5sZXRzZW5jcnlwdC5vcmcwggEFBgorBgEEAdZ5AgQCBIH2BIHz\nAPEAdwDfpV6raIJPH2yt7rhfTj5a6s2iEqRqXo47EsAgRFwqcwAAAX9hEiCqAAAE\nAwBIMEYCIQDCHQT3cGN+UbVN8iuOtoGuqvQqHcuL4ZT9cLFhYRpQiQIhALBGEdgC\nYbnzAgll1echwZka+3+En86S0Yfu6cvNwDejAHYAKXm+8J45OSHwVnOfY6V35b5X\nfZxgCvj5TV0mXCVdx4QAAAF/YRIgnQAABAMARzBFAiEA//V0mz4DogmdXHYvbv75\n0yA/9TeBwRC3Dl33H2BPTxwCIAOEPv6sDEMloV0VXswiI+3cKLIFOYAKjjsVywWw\nHYUbMA0GCSqGSIb3DQEBCwUAA4IBAQAXfAJZ/YYpTiOl6s/5jFNiXAoQl8wqhkbm\nwRkfXkSppkrTnNmSOp8rlnqRB6NvCwADNeLPePY6ORnGbcLfoz91gQ8eZxZwqzUV\nqCZNc2dnK/f2xkMjBCorRWLJZjcLLIffRxUKcceo02N9jbbv2Xcb7BGprvMQmJNd\nM29TXS7wMelKtfbx4ppOSSSW41cixO+eCsGyCyxslTczKm+Uraa4WEId1uzXKeaV\nBhHFmIMeuNIqfW7p06s70DeHfaUgc9WoUVjF/VHJ8m08Q/NFvEZRfbP0E3GXm4VC\nkck3boIvzwjE9Q/V17sBe7OSm8eVDNNG+0VygwhvZrvdCW1tqF11\n-----END CERTIFICATE-----\n",
            "-----BEGIN CERTIFICATE-----\nMIIFFjCCAv6gAwIBAgIRAJErCErPDBinU/bWLiWnX1owDQYJKoZIhvcNAQELBQAw\nTzELMAkGA1UEBhMCVVMxKTAnBgNVBAoTIEludGVybmV0IFNlY3VyaXR5IFJlc2Vh\ncmNoIEdyb3VwMRUwEwYDVQQDEwxJU1JHIFJvb3QgWDEwHhcNMjAwOTA0MDAwMDAw\nWhcNMjUwOTE1MTYwMDAwWjAyMQswCQYDVQQGEwJVUzEWMBQGA1UEChMNTGV0J3Mg\nRW5jcnlwdDELMAkGA1UEAxMCUjMwggEiMA0GCSqGSIb3DQEBAQUAA4IBDwAwggEK\nAoIBAQC7AhUozPaglNMPEuyNVZLD+ILxmaZ6QoinXSaqtSu5xUyxr45r+XXIo9cP\nR5QUVTVXjJ6oojkZ9YI8QqlObvU7wy7bjcCwXPNZOOftz2nwWgsbvsCUJCWH+jdx\nsxPnHKzhm+/b5DtFUkWWqcFTzjTIUu61ru2P3mBw4qVUq7ZtDpelQDRrK9O8Zutm\nNHz6a4uPVymZ+DAXXbpyb/uBxa3Shlg9F8fnCbvxK/eG3MHacV3URuPMrSXBiLxg\nZ3Vms/EY96Jc5lP/Ooi2R6X/ExjqmAl3P51T+c8B5fWmcBcUr2Ok/5mzk53cU6cG\n/kiFHaFpriV1uxPMUgP17VGhi9sVAgMBAAGjggEIMIIBBDAOBgNVHQ8BAf8EBAMC\nAYYwHQYDVR0lBBYwFAYIKwYBBQUHAwIGCCsGAQUFBwMBMBIGA1UdEwEB/wQIMAYB\nAf8CAQAwHQYDVR0OBBYEFBQusxe3WFbLrlAJQOYfr52LFMLGMB8GA1UdIwQYMBaA\nFHm0WeZ7tuXkAXOACIjIGlj26ZtuMDIGCCsGAQUFBwEBBCYwJDAiBggrBgEFBQcw\nAoYWaHR0cDovL3gxLmkubGVuY3Iub3JnLzAnBgNVHR8EIDAeMBygGqAYhhZodHRw\nOi8veDEuYy5sZW5jci5vcmcvMCIGA1UdIAQbMBkwCAYGZ4EMAQIBMA0GCysGAQQB\ngt8TAQEBMA0GCSqGSIb3DQEBCwUAA4ICAQCFyk5HPqP3hUSFvNVneLKYY611TR6W\nPTNlclQtgaDqw+34IL9fzLdwALduO/ZelN7kIJ+m74uyA+eitRY8kc607TkC53wl\nikfmZW4/RvTZ8M6UK+5UzhK8jCdLuMGYL6KvzXGRSgi3yLgjewQtCPkIVz6D2QQz\nCkcheAmCJ8MqyJu5zlzyZMjAvnnAT45tRAxekrsu94sQ4egdRCnbWSDtY7kh+BIm\nlJNXoB1lBMEKIq4QDUOXoRgffuDghje1WrG9ML+Hbisq/yFOGwXD9RiX8F6sw6W4\navAuvDszue5L3sz85K+EC4Y/wFVDNvZo4TYXao6Z0f+lQKc0t8DQYzk1OXVu8rp2\nyJMC6alLbBfODALZvYH7n7do1AZls4I9d1P4jnkDrQoxB3UqQ9hVl3LEKQ73xF1O\nyK5GhDDX8oVfGKF5u+decIsH4YaTw7mP3GFxJSqv3+0lUFJoi5Lc5da149p90Ids\nhCExroL1+7mryIkXPeFM5TgO9r0rvZaBFOvV2z0gp35Z0+L4WPlbuEjN/lxPFin+\nHlUjr8gRsI3qfJOQFy/9rKIJR0Y/8Omwt/8oTWgy1mdeHmmjk7j1nYsvC9JSQ6Zv\nMldlTTKB3zhThV1+XWYp6rjd5JW1zbVWEkLNxE7GJThEUG3szgBVGP7pSWTUTsqX\nnLRbwHOoq7hHwg==\n-----END CERTIFICATE-----\n",
            "-----BEGIN CERTIFICATE-----\nMIIFazCCA1OgAwIBAgIRAIIQz7DSQONZRGPgu2OCiwAwDQYJKoZIhvcNAQELBQAw\nTzELMAkGA1UEBhMCVVMxKTAnBgNVBAoTIEludGVybmV0IFNlY3VyaXR5IFJlc2Vh\ncmNoIEdyb3VwMRUwEwYDVQQDEwxJU1JHIFJvb3QgWDEwHhcNMTUwNjA0MTEwNDM4\nWhcNMzUwNjA0MTEwNDM4WjBPMQswCQYDVQQGEwJVUzEpMCcGA1UEChMgSW50ZXJu\nZXQgU2VjdXJpdHkgUmVzZWFyY2ggR3JvdXAxFTATBgNVBAMTDElTUkcgUm9vdCBY\nMTCCAiIwDQYJKoZIhvcNAQEBBQADggIPADCCAgoCggIBAK3oJHP0FDfzm54rVygc\nh77ct984kIxuPOZXoHj3dcKi/vVqbvYATyjb3miGbESTtrFj/RQSa78f0uoxmyF+\n0TM8ukj13Xnfs7j/EvEhmkvBioZxaUpmZmyPfjxwv60pIgbz5MDmgK7iS4+3mX6U\nA5/TR5d8mUgjU+g4rk8Kb4Mu0UlXjIB0ttov0DiNewNwIRt18jA8+o+u3dpjq+sW\nT8KOEUt+zwvo/7V3LvSye0rgTBIlDHCNAymg4VMk7BPZ7hm/ELNKjD+Jo2FR3qyH\nB5T0Y3HsLuJvW5iB4YlcNHlsdu87kGJ55tukmi8mxdAQ4Q7e2RCOFvu396j3x+UC\nB5iPNgiV5+I3lg02dZ77DnKxHZu8A/lJBdiB3QW0KtZB6awBdpUKD9jf1b0SHzUv\nKBds0pjBqAlkd25HN7rOrFleaJ1/ctaJxQZBKT5ZPt0m9STJEadao0xAH0ahmbWn\nOlFuhjuefXKnEgV4We0+UXgVCwOPjdAvBbI+e0ocS3MFEvzG6uBQE3xDk3SzynTn\njh8BCNAw1FtxNrQHusEwMFxIt4I7mKZ9YIqioymCzLq9gwQbooMDQaHWBfEbwrbw\nqHyGO0aoSCqI3Haadr8faqU9GY/rOPNk3sgrDQoo//fb4hVC1CLQJ13hef4Y53CI\nrU7m2Ys6xt0nUW7/vGT1M0NPAgMBAAGjQjBAMA4GA1UdDwEB/wQEAwIBBjAPBgNV\nHRMBAf8EBTADAQH/MB0GA1UdDgQWBBR5tFnme7bl5AFzgAiIyBpY9umbbjANBgkq\nhkiG9w0BAQsFAAOCAgEAVR9YqbyyqFDQDLHYGmkgJykIrGF1XIpu+ILlaS/V9lZL\nubhzEFnTIZd+50xx+7LSYK05qAvqFyFWhfFQDlnrzuBZ6brJFe+GnY+EgPbk6ZGQ\n3BebYhtF8GaV0nxvwuo77x/Py9auJ/GpsMiu/X1+mvoiBOv/2X/qkSsisRcOj/KK\nNFtY2PwByVS5uCbMiogziUwthDyC3+6WVwW6LLv3xLfHTjuCvjHIInNzktHCgKQ5\nORAzI4JMPJ+GslWYHb4phowim57iaztXOoJwTdwJx4nLCgdNbOhdjsnvzqvHu7Ur\nTkXWStAmzOVyyghqpZXjFaH3pO3JLF+l+/+sKAIuvtd7u+Nxe5AW0wdeRlN8NwdC\njNPElpzVmbUq4JUagEiuTDkHzsxHpFKVK7q4+63SM1N95R1NbdWhscdCb+ZAJzVc\noyi3B43njTOQ5yOf+1CceWxG1bQVs5ZufpsMljq4Ui0/1lvh+wjChP4kqKOJ2qxq\n4RgqsahDYVvTH9w7jXbyLeiNdd8XM2w9U/t7y0Ff/9yi0GE44Za4rF2LN9d11TPA\nmRGunUHBcnWEvgJBQl9nJEiU0Zsnvgc/ubhPgXRR4Xq37Z0j4r7g1SgEEzwxA57d\nemyPxgcYxn/eR44/KJ4EBs+lVDR3veyJm+kXQ99b21/+jh5Xos1AnX5iItreGCc=\n-----END CERTIFICATE-----\n"
          ],
          "dhparams": null,
          "versions": [
            "-TLSv1",
            "-SSLv2",
            "-SSLv3",
            "-TLSv1.1",
            "TLSv1.2",
            "TLSv1.3"
          ],
          "acceptable_cas": [],
          "tlsext": [
            {
              "id": 65281,
              "name": "renegotiation_info"
            },
            {
              "id": 11,
              "name": "ec_point_formats"
            },
            {
              "id": 35,
              "name": "session_ticket"
            },
            {
              "id": 5,
              "name": "status_request"
            }
          ],
          "ja3s": "452c3b3abf0ed48df1b925f6977db72b",
          "cert": {
            "sig_alg": "sha256WithRSAEncryption",
            "issued": "20220306201052Z",
            "expires": "20220604201051Z",
            "expired": false,
            "version": 2,
            "extensions": [
              {
                "critical": true,
                "data": "\\x03\\x02\\x05\\xa0",
                "name": "keyUsage"
              },
              {
                "data": "0\\x14\\x06\\x08+\\x06\\x01\\x05\\x05\\x07\\x03\\x01\\x06\\x08+\\x06\\x01\\x05\\x05\\x07\\x03\\x02",
                "name": "extendedKeyUsage"
              },
              {
                "critical": true,
                "data": "0\\x00",
                "name": "basicConstraints"
              },
              {
                "data": "\\x04\\x14AuJ\\xce\\x94\\xf2\\xa5\\xd4\\x88\\xeaF\\xde\nT\"\\xb7{\\x0e\\xdd\\x08",
                "name": "subjectKeyIdentifier"
              },
              {
                "data": "0\\x16\\x80\\x14\\x14.\\xb3\\x17\\xb7XV\\xcb\\xaeP @\\xe6\\x1f\\xaf\\x9d\\x8b\\x14\\xc2\\xc6",
                "name": "authorityKeyIdentifier"
              },
              {
                "data": "0G0!\\x06\\x08+\\x06\\x01\\x05\\x05\\x070\\x01\\x86\\x15http://r3.o.lencr.org0\"\\x06\\x08+\\x06\\x01\\x05\\x05\\x070\\x02\\x86\\x16http://r3.i.lencr.org/",
                "name": "authorityInfoAccess"
              },
              {
                "data": "0\\x18\\x82\\x16staging.stephenfry.com",
                "name": "subjectAltName"
              },
              {
                "data": "0C0\\x08\\x06\\x06g\\x81\\x0c\\x01\\x02\\x0107\\x06\\x0b+\\x06\\x01\\x04\\x01\\x82\\xdf\\x13\\x01\\x01\\x010(0&\\x06\\x08+\\x06\\x01\\x05\\x05\\x07\\x02\\x01\\x16\\x1ahttp://cps.letsencrypt.org",
                "name": "certificatePolicies"
              },
              {
                "data": "\\x04\\x81\\xf3\\x00\\xf1\\x00w\\x00\\xdf\\xa5^\\xabh\\x82O\\x1fl\\xad\\xee\\xb8_N>Z\\xea\\xcd\\xa2\\x12\\xa4j^\\x8e;\\x12\\xc0 D\\\\*s\\x00\\x00\\x01\\x7fa\\x12 \\xaa\\x00\\x00\\x04\\x03\\x00H0F\\x02!\\x00\\xc2\\x1d\\x04\\xf7pc~Q\\xb5M\\xf2+\\x8e\\xb6\\x81\\xae\\xaa\\xf4*\\x1d\\xcb\\x8b\\xe1\\x94\\xfdp\\xb1aa\\x1aP\\x89\\x02!\\x00\\xb0F\\x11\\xd8\\x02a\\xb9\\xf3\\x02 e\\xd5\\xe7!\\xc1\\x99\\x1a\\xfb\\x7f\\x84\\x9f\\xce\\x92\\xd1\\x87\\xee\\xe9\\xcb\\xcd\\xc07\\xa3\\x00v\\x00)y\\xbe\\xf0\\x9e99!\\xf0Vs\\x9fc\\xa5w\\xe5\\xbeW}\\x9c`\n\\xf8\\xf9M]&\\\\%]\\xc7\\x84\\x00\\x00\\x01\\x7fa\\x12 \\x9d\\x00\\x00\\x04\\x03\\x00G0E\\x02!\\x00\\xff\\xf5t\\x9b>\\x03\\xa2 \\x9d\\/n\\xfe\\xf9\\xd3 ?\\xf57\\x81\\xc1\\x10\\xb7\\x0e]\\xf7\\x1f`OO\\x1c\\x02 \\x03\\x84>\\xfe\\xac\\x0cC%\\xa1]\\x15^\\xcc\"#\\xed\\xdc(\\xb2\\x059\\x80\n\\x8e;\\x15\\xcb\\x05\\xb0\\x1d\\x85\\x1b",
                "name": "ct_precert_scts"
              }
            ],
            "fingerprint": {
              "sha256": "f81b66fb065678bc87afcaf078749654ce9272fa7bc8641db180e535e3c7e0c6",
              "sha1": "e9daf2fb32bffcb01ab1c60d59d30e29f3384040"
            },
            "serial": 3.1442496670791655e+41,
            "subject": {
              "CN": "staging.stephenfry.com"
            },
            "pubkey": {
              "type": "rsa",
              "bits": 2048
            },
            "issuer": {
              "C": "US",
              "CN": "R3",
              "O": "Let's Encrypt"
            }
          },
          "cipher": {
            "version": "TLSv1/SSLv3",
            "bits": 256,
            "name": "ECDHE-RSA-AES256-GCM-SHA384"
          },
          "trust": {
            "revoked": false,
            "browser": {
              "mozilla": true,
              "apple": true,
              "microsoft": true
            }
          },
          "handshake_states": [
            "before/connect initialization",
            "SSLv2/v3 write client hello",
            "SSLv2/v3 read server hello",
            "SSLv3/TLS read server hello",
            "SSLv3/TLS read server certificate",
            "SSLv3/TLS read server key exchange",
            "SSLv3/TLS read server done",
            "SSLv3/TLS write client key exchange",
            "SSLv3/TLS write change cipher spec",
            "SSLv3/TLS write finished",
            "SSLv3/TLS flush data",
            "SSLv3/TLS read server session ticket",
            "SSLv3/TLS read finished",
            "SSL negotiation finished successfully"
          ],
          "alpn": [
            "h2",
            "http/1.1"
          ],
          "ocsp": {
            "version": "1",
            "response_status": "successful",
            "responder_id": "C = US, O = Let's Encrypt, CN = R3",
            "cert_status": "good",
            "produced_at": "2022-03-24 09:10:00",
            "signature_algorithm": "sha256WithRSAEncryption",
            "next_update": "2022-03-31 08:59:58",
            "this_update": "2022-03-24 09:00:00",
            "certificate_id": {
              "hash_algorithm": "sha1",
              "issuer_name_hash": "48DAC9A0FB2BD32D4FF0DE68D2F567B735F9B3C4",
              "issuer_name_key": "142EB317B75856CBAE500940E61FAF9D8B14C2C6",
              "serial_number": "039C030DDD54B262B50089D76048B8998068"
            }
          }
        },
        "hostnames": [
          "fry-vip-01.positive-dedicated.net",
          "staging.stephenfry.com"
        ],
        "org": "Positive Infrastructure",
        "data": "HTTP/1.1 200 OK\r\nServer: nginx/1.18.0\r\nDate: Fri, 25 Mar 2022 00:50:26 GMT\r\nContent-Type: text/html\r\nContent-Length: 10701\r\nConnection: keep-alive\r\nLast-Modified: Fri, 16 Jul 2021 14:22:05 GMT\r\nVary: Accept-Encoding\r\nCache-Control: max-age=600\r\nX-Varnish: 4603538 4083004\r\nAge: 46954\r\nVia: 1.1 varnish (Varnish/6.5)\r\nETag: W/\"29cd-5c73e4fddd96f-gzip\"\r\nx-cache: HIT cachable\r\nAccept-Ranges: bytes\r\n\r\n",
        "asn": "AS21260",
        "cpe23": [
          "cpe:2.3:a:igor_sysoev:nginx:1.18.0"
        ],
        "isp": "The Positive Internet Company Ltd",
        "cpe": [
          "cpe:/a:igor_sysoev:nginx:1.18.0"
        ],
        "domains": [
          "positive-dedicated.net",
          "stephenfry.com"
        ],
        "ip_str": "80.87.129.232",
        "os": null,
        "_shodan": {
          "crawler": "3f1279c6853212fb475ce5da28a7fdac617a5bd4",
          "options": {
            "referrer": "9fe4098c-1a4c-434d-9e80-41a86edd0ae1"
          },
          "id": "3940851b-b0a3-48ca-80f0-7ed00f550030",
          "module": "https",
          "ptr": true
        },
        "opts": {
          "vulns": [],
          "heartbleed": "2022/03/25 00:50:37 80.87.129.232:443 - SAFE\n"
        }
      }
    ],
    "asn": "AS21260",
    "ip_str": "80.87.129.232"
  }